pytoyoda/__init__.py
pytoyoda/api.py
pytoyoda/client.py
pytoyoda/const.py
pytoyoda/controller.py
pytoyoda/exceptions.py
pytoyoda/models/__init__.py
pytoyoda/models/climate.py
pytoyoda/models/dashboard.py
pytoyoda/models/electric_status.py
pytoyoda/models/endpoints/__init__.py
pytoyoda/models/endpoints/account.py
pytoyoda/models/endpoints/climate.py
pytoyoda/models/endpoints/command.py
pytoyoda/models/endpoints/common.py
pytoyoda/models/endpoints/electric.py
pytoyoda/models/endpoints/location.py
pytoyoda/models/endpoints/notifications.py
pytoyoda/models/endpoints/service_history.py
pytoyoda/models/endpoints/status.py
pytoyoda/models/endpoints/telemetry.py
pytoyoda/models/endpoints/trips.py
pytoyoda/models/endpoints/vehicle_guid.py
pytoyoda/models/endpoints/vehicle_health.py
pytoyoda/models/location.py
pytoyoda/models/lock_status.py
pytoyoda/models/nofication.py
pytoyoda/models/service_history.py
pytoyoda/models/summary.py
pytoyoda/models/trips.py
pytoyoda/models/vehicle.py
pytoyoda/py.typed
pytoyoda/utils/__init__.py
pytoyoda/utils/conversions.py
pytoyoda/utils/formatters.py
pytoyoda/utils/helpers.py
pytoyoda/utils/locale.py
pytoyoda/utils/log_utils.py
pytoyoda/utils/models.py
pytoyoda-4.2.0.dist-info/METADATA
pytoyoda-4.2.0.dist-info/WHEEL
pytoyoda-4.2.0.dist-info/licenses/LICENSE
pytoyoda-4.2.0.dist-info/RECORD
