Metadata-Version: 2.4
Name: pytoyoda
Version: 4.2.0
Summary: Python client for Toyota Connected Services Europe.
License-Expression: MIT
License-File: LICENSE
Keywords: Toyota,Car,MYT
Author: CM000n
Author-email: simon.hoerrle@gmail.com
Requires-Python: >=3.9,<4.0
Classifier: Development Status :: 4 - Beta
Classifier: Environment :: Console
Classifier: Intended Audience :: Developers
Classifier: License :: OSI Approved :: MIT License
Classifier: Operating System :: OS Independent
Classifier: Programming Language :: Python :: 3
Classifier: Programming Language :: Python :: 3.9
Classifier: Programming Language :: Python :: 3.10
Classifier: Programming Language :: Python :: 3.11
Classifier: Programming Language :: Python :: 3.12
Classifier: Programming Language :: Python :: 3.13
Classifier: Programming Language :: Python :: 3.14
Requires-Dist: arrow (>=1.1,<2.0)
Requires-Dist: hishel (>=0.1.0,<0.2.0)
Requires-Dist: httpx (>=0.28.1,<0.29.0)
Requires-Dist: importlib-metadata (>=8.0.0,<9.0.0)
Requires-Dist: langcodes (>=3.1,<4.0)
Requires-Dist: loguru (>=0.7.3,<0.8.0)
Requires-Dist: pydantic (>=2.10.4,<3.0.0)
Requires-Dist: pyjwt (>=2.8.0,<3.0.0)
Project-URL: Bug Tracker, https://github.com/pytoyoda/pytoyoda/issues
Project-URL: Homepage, https://pytoyoda.github.io/pytoyoda/pytoyoda.html
Project-URL: Repository, https://github.com/pytoyoda/pytoyoda
Project-URL: Release Notes, https://github.com/pytoyoda/pytoyoda/releases
